dry_monads/__init__.py
dry_monads/do_notation.py
dry_monads/either.py
dry_monads/functions.py
dry_monads/maybe.py
dry_monads/primitives/__init__.py
dry_monads/primitives/exceptions.py
dry_monads/primitives/monad.py
dry_monads/primitives/types.py
dry_monads-0.2.0.dist-info/LICENSE
dry_monads-0.2.0.dist-info/WHEEL
dry_monads-0.2.0.dist-info/METADATA
dry_monads-0.2.0.dist-info/RECORD
