Metadata-Version: 2.1
Name: dry-monads
Version: 0.2.0
Summary: Monads for python made simple and safe.
Home-page: https://dry-monads.readthedocs.io
License: MIT
Keywords: functional programming,fp,monads,monad,type-safety,mypy,railway-oriented-programming
Author: sobolevn
Author-email: mail@sobolevn.me
Requires-Python: >=3.6,<4.0
Classifier: Development Status :: 3 - Alpha
Classifier: Intended Audience :: Developers
Classifier: License :: OSI Approved :: MIT License
Classifier: Operating System :: OS Independent
Classifier: Programming Language :: Python :: 3
Classifier: Programming Language :: Python :: 3.6
Classifier: Programming Language :: Python :: 3.7
Classifier: Topic :: Software Development :: Libraries :: Python Modules
Classifier: Topic :: Utilities
Requires-Dist: typing-extensions (>=3.7,<4.0)
Project-URL: Repository, https://github.com/sobolevn/dry-monads
